{
  "document_id": "IEC 17065",
  "file_path": "data/raw\\scc.ca\\2012\\asb_soa_10052-labtest_v24_2025-05-14_en.pdf",
  "title": "",
  "abstract": "Page 1 of 13 \nASB_JA_CBAP-Scope-Template_v11_2022-11-24 \n \nCERTIFICATION BODY ACCREDITATION PROGRAM (CBAP) \nScope of Accreditation \nAccredited Legal Entity: \nLabTest Certification Inc. \nContact Name: \nKavinder Dhillon \nLOCATION A  \nAddress: \n205 \u2013 8291 92 Street \nDelta, British Columbia \nV4G 0A4 \n \nTelephone: \n604 247-0444 \nTelefax: \n604 247-0442 \nWebsite: \nlabtestcert.com \nEmail: \nkdhillon@labtestcert.com \n \n \nSCC File Number: \n10052 \nAccreditation Standard: \nISO/IEC 17065:2012 \u2013 Conformity ass",
  "publication_date": "2025-05-14",
  "organization": "ISO"
}