{
  "document_id": "IEC 17065",
  "file_path": "data/raw\\scc.ca\\2012\\asb_soa_10067_scope_v13_2025-02-10_en.pdf",
  "title": "",
  "abstract": "Page 1 of 3 \nASB_JA_CBAP-Scope-Template_v11_2022-11-24 \n \n \nCERTIFICATION BODY ACCREDITATION PROGRAM (CBAP) \nScope of Accreditation \n \nAccredited Legal Entity: \nICC NTA, LLC \nContact Name: \nVicky Brown, Quality Assurance Manager \nLOCATION A \nAddress: \n305 North Oakland Avenue \nNappanee, IN \n46550 \nTelephone: \n574 773-1678 \nFax: \n574 773-2260 \nWebsite: \nwww.icc-nta.org \nEmail: \nvbrown@icc-nta.org \n \nSCC File Number: \n10067 \nAccreditation Standard: \nISO/IEC 17065:2012 \u2013 Conformity assessment \u2014 \nRe",
  "publication_date": "2025-02-10",
  "organization": "ISO"
}